spotpy/__init__.py
spotpy/_version.py
spotpy/analyser.py
spotpy/cli.py
spotpy/describe.py
spotpy/likelihoods.py
spotpy/objectivefunctions.py
spotpy/parameter.py
spotpy/algorithms/__init__.py
spotpy/algorithms/_algorithm.py
spotpy/algorithms/abc.py
spotpy/algorithms/dds.py
spotpy/algorithms/demcz.py
spotpy/algorithms/dream.py
spotpy/algorithms/efast.py
spotpy/algorithms/fast.py
spotpy/algorithms/fscabc.py
spotpy/algorithms/lhs.py
spotpy/algorithms/list_sampler.py
spotpy/algorithms/mc.py
spotpy/algorithms/mcmc.py
spotpy/algorithms/mle.py
spotpy/algorithms/nsgaii.py
spotpy/algorithms/padds.py
spotpy/algorithms/rope.py
spotpy/algorithms/sa.py
spotpy/algorithms/sceua.py
spotpy/database/__init__.py
spotpy/database/base.py
spotpy/database/csv.py
spotpy/database/hdf5.py
spotpy/database/ram.py
spotpy/database/sql.py
spotpy/examples/__init__.py
spotpy/examples/spot_setup_ackley.py
spotpy/examples/spot_setup_cmf1d.py
spotpy/examples/spot_setup_cmf_lumped.py
spotpy/examples/spot_setup_dds.py
spotpy/examples/spot_setup_dtlz1.py
spotpy/examples/spot_setup_griewank.py
spotpy/examples/spot_setup_hymod_exe.py
spotpy/examples/spot_setup_hymod_python.py
spotpy/examples/spot_setup_hymod_python_pareto.py
spotpy/examples/spot_setup_hymod_unix.py
spotpy/examples/spot_setup_rosenbrock.py
spotpy/examples/spot_setup_standardnormal.py
spotpy/examples/cmf_data/__init__.py
spotpy/examples/cmf_data/driver_data_site24.csv
spotpy/examples/cmf_data/fulda_climate.csv
spotpy/examples/cmf_data/soilmoisture_site24.csv
spotpy/examples/hymod_exe/HYMODsilent.exe
spotpy/examples/hymod_exe/Param.in
spotpy/examples/hymod_exe/__init__.py
spotpy/examples/hymod_exe/bound.txt
spotpy/examples/hymod_exe/bound_units.xlsx
spotpy/examples/hymod_exe/hymod_input.csv
spotpy/examples/hymod_exe/license.txt
spotpy/examples/hymod_python/__init__.py
spotpy/examples/hymod_python/hymod.py
spotpy/examples/hymod_python/hymod_input.csv
spotpy/examples/hymod_unix/__init__.py
spotpy/examples/hymod_unix/bound.txt
spotpy-1.6.4.dist-info/LICENSE
spotpy-1.6.4.dist-info/METADATA
spotpy-1.6.4.dist-info/WHEEL
spotpy-1.6.4.dist-info/top_level.txt
spotpy-1.6.4.dist-info/RECORD
