Metadata-Version: 2.2
Name: spotpy
Version: 1.6.4
Summary: A Statistical Parameter Optimization Tool.
Author: Philipp Kraft, Alejandro Chamorro-Chavez, Lutz Breuer
Author-email: Tobias Houska <tobias.houska@umwelt.uni-giessen.de>, Sebastian Müller <sebastian.mueller@ufz.de>, Anna Herzog <anna.herzog@uni-potsdam.de>
Maintainer-email: Tobias Houska <tobias.houska@umwelt.uni-giessen.de>
License: The MIT License (MIT)
Project-URL: Changelog, https://github.com/thouska/spotpy/blob/master/CHANGELOG.md
Project-URL: Conda-Forge, https://anaconda.org/conda-forge/spotpy
Project-URL: Documentation, https://spotpy.readthedocs.io
Project-URL: Homepage, https://github.com/thouska/spotpy
Project-URL: Source, https://github.com/thouska/spotpy
Project-URL: Tracker, https://github.com/thouska/spotpy/issues
Keywords: Monte Carlo,MCMC,MLE,SCE-UA,Simulated Annealing,DE-MCz,DREAM,ROPE,Artifical Bee Colony,DDS,PA-DDS,NSGAii,Uncertainty,Calibration,Model,Signatures
Classifier: Development Status :: 5 - Production/Stable
Classifier: Intended Audience :: Developers
Classifier: Intended Audience :: End Users/Desktop
Classifier: Intended Audience :: Science/Research
Classifier: Intended Audience :: Education
Classifier: License :: OSI Approved :: MIT License
Classifier: Natural Language :: English
Classifier: Operating System :: Unix
Classifier: Operating System :: Microsoft
Classifier: Operating System :: MacOS
Classifier: Programming Language :: Python
Classifier: Programming Language :: Python :: 3
Classifier: Programming Language :: Python :: 3 :: Only
Classifier: Programming Language :: Python :: 3.12
Classifier: Topic :: Scientific/Engineering
Classifier: Topic :: Scientific/Engineering :: Hydrology
Classifier: Topic :: Scientific/Engineering :: Mathematics
Classifier: Topic :: Scientific/Engineering :: Physics
Classifier: Topic :: Utilities
Requires-Python: >=3.9
License-File: LICENSE
Requires-Dist: numpy>=2.0
Requires-Dist: scipy>=1.5.0
Provides-Extra: plotting
Requires-Dist: pandas>=1; extra == "plotting"
Requires-Dist: matplotlib>=3; extra == "plotting"
Provides-Extra: test
Requires-Dist: pytest-cov>=3; extra == "test"
Requires-Dist: numba; extra == "test"
Requires-Dist: pathos; extra == "test"
Requires-Dist: matplotlib; extra == "test"
Requires-Dist: click; extra == "test"
Requires-Dist: pandas; extra == "test"
Requires-Dist: tables; extra == "test"
Requires-Dist: docutils; extra == "test"
